unixsig/__init__.py
unixsig/listener.py
unixsig-0.1.4.dist-info/LICENSE.txt
unixsig-0.1.4.dist-info/METADATA
unixsig-0.1.4.dist-info/WHEEL
unixsig-0.1.4.dist-info/top_level.txt
unixsig-0.1.4.dist-info/RECORD
