Metadata-Version: 2.1
Name: unixsig
Version: 0.1.4
Summary: Python Package to Handle Unix Signals.
Home-page: https://github.com/clivern/unixsig/
Author: Clivern
Author-email: hello@clivern.com
License: MIT
Project-URL: Documentation, https://github.com/clivern/unixsig/
Project-URL: Source, https://github.com/clivern/unixsig/
Project-URL: Changelog, https://github.com/Clivern/unixsig/blob/main/CHANGELOG.rst
Project-URL: Tracker, https://github.com/Clivern/unixsig/issues
Project-URL: Download, https://pypi.org/project/unixsig/#files
Platform: any
Classifier: Development Status :: 5 - Production/Stable
Classifier: Programming Language :: Python
Classifier: License :: OSI Approved :: MIT License
Requires-Python: >=3.6
License-File: LICENSE.txt
Requires-Dist: importlib-metadata ; python_version < "3.8"
Provides-Extra: testing
Requires-Dist: setuptools ; extra == 'testing'
Requires-Dist: pytest ; extra == 'testing'
Requires-Dist: pytest-cov ; extra == 'testing'
